influxdb_wrapper/__init__.py
influxdb_wrapper/db_conn.py
influxdb_wrapper/influxdb_conn.py
influxdb_wrapper/mockdb_conn.py
tests/__init__.py
tests/test_000.py
influxdb_wrapper-0.0.5.dist-info/METADATA
influxdb_wrapper-0.0.5.dist-info/WHEEL
influxdb_wrapper-0.0.5.dist-info/top_level.txt
influxdb_wrapper-0.0.5.dist-info/RECORD
