Metadata-Version: 2.1
Name: influxdb-wrapper
Version: 0.0.5
Summary: DB management wrapper over influxDB
Home-page: https://github.com/Phornee/influxdb_wrapper
Author: Ismael Raya
Author-email: phornee@gmail.com
License: UNKNOWN
Platform: UNKNOWN
Classifier: Programming Language :: Python :: 3
Classifier: License :: OSI Approved :: MIT License
Classifier: Operating System :: OS Independent
Requires-Python: >=3.6
Requires-Dist: dnspython (==1.16.0)
Requires-Dist: influxdb (>=5.3.1)
